{
    "prime": {
        "introit":  [
            "Deus in adjutorium meum intende.",
            "Domine ad adjuvandum me festina."          
        ],
        "hymn": [
            "Iam lucis orto sidere,",
            "Deum precemur supplices,",
            "Ut in diurnis actibus",
            "Nos servet a nocentibus.",
            "",
            "Linguam refrenans temperet,",
            "Ne litis horror insonet:",
            "Visum fovendo contegat,",
            "Ne vanitates hauriat.",
            "",
            "Sint pura cordis intima,",
            "Absistat et vecordia:",
            "Carnis terat superbiam",
            "Potus cibique parcitas.",
            "",
            "Ut cum dies abscesserit,",
            "Noctemque sors reduxerit,",
            "Mundi per abstinentiam",
            "Ipsi canamus gloriam."
        ],
        "chapter": "1 Thess 5:17",
        "versicle": "",
        "closing": "md 8-9",
        "antiphons": {
            "default": "Regi saeculorum...",
            "seasons": {
                "lent": "Panem caeli dedit eis...",
                "advent": "Ecce Dominus veniet..."
            },
            "feasts": {
                "christmas": "Hodie Christus natus est..."
            }
        },
        "psalms": {
            "sunday": [
                {"number": "118", "category": "aleph"},
                {"number": "118", "category": "beth"},
                {"number": "118", "category": "gimel"},
                {"number": "118", "category": "daleth"}
            ],
            "monday": [
                {"number": "1"},
                {"number": "2"},
                {"number": "6"}
            ],
            "tuesday": [
                {"number": "7"},
                {"number": "8"},
                {"number": "9", "category": "A"}
            ],
            "wednesday": [
                {"number": "9", "category": "B"},
                {"number": "10"},
                {"number": "11"}
            ],
            "thursday": [
                {"number": "12"},
                {"number": "13"},
                {"number": "14"}
            ],
            "friday": [
                {"number": "15"},
                {"number": "16"},
                {"number": "17", "category": "A"}
            ],
            "saturday": [
                {"number": "17", "category": "B"},
                {"number": "18"},
                {"number": "19"}
            ]
        }
    }
}